tests/__init__.py
tests/test_tqdl.py
tqdl/__init__.py
tqdl/_version.py
tqdl/core.py
tqdl-0.0.4.dist-info/METADATA
tqdl-0.0.4.dist-info/RECORD
tqdl-0.0.4.dist-info/WHEEL
tqdl-0.0.4.dist-info/top_level.txt
